win_alias.py
win_alias-1.0.4.dist-info/entry_points.txt
win_alias-1.0.4.dist-info/LICENSE.txt
win_alias-1.0.4.dist-info/WHEEL
win_alias-1.0.4.dist-info/METADATA
win_alias-1.0.4.dist-info/RECORD
