Metadata-Version: 2.3
Name: win-alias
Version: 1.0.4
Summary: A simple CLI tool to create Windows aliases.
Author: EverythingPython
Requires-Python: >=3.11
Requires-Dist: click>=8.0.1
Requires-Dist: charset-normalizer==3.4.1
Requires-Dist: colorama==0.4.6
Requires-Dist: docutils==0.21.2
Requires-Dist: flit==3.10.1
Requires-Dist: idna==3.10
Requires-Dist: requests==2.32.3
Requires-Dist: tomli-w==1.2.0
Requires-Dist: urllib3==2.3.0
Project-URL: Homepage, https://github.com/everythingpython/win-alias
Project-URL: Issues, https://github.com/everythingpython/win-alias/issues
